gitlab_jobs.py
gitlab_jobs-1.2.1.dist-info/LICENSE
gitlab_jobs-1.2.1.dist-info/METADATA
gitlab_jobs-1.2.1.dist-info/WHEEL
gitlab_jobs-1.2.1.dist-info/entry_points.txt
gitlab_jobs-1.2.1.dist-info/top_level.txt
gitlab_jobs-1.2.1.dist-info/RECORD
